LICENSE
MANIFEST.in
README.rst
requirements.txt
setup.cfg
setup.py
test-requirements.txt
bear_installation_tool/__init__.py
bear_installation_tool/installation_tool.py
bear_installation_tool.egg-info/PKG-INFO
bear_installation_tool.egg-info/SOURCES.txt
bear_installation_tool.egg-info/dependency_links.txt
bear_installation_tool.egg-info/entry_points.txt
bear_installation_tool.egg-info/requires.txt
bear_installation_tool.egg-info/top_level.txt